README.txt
setup.py
autoqueue/__init__.py
autoqueue.egg-info/PKG-INFO
autoqueue.egg-info/SOURCES.txt
autoqueue.egg-info/dependency_links.txt
autoqueue.egg-info/top_level.txt
mirage/__init__.py