Metadata-Version: 1.1
Name: autoqueue
Version: 0.2beta1
Summary: A cross music player plugin that queues similar tracks.
Home-page: https://launchpad.net/autoqueue
Author: Eric Casteleijn
Author-email: thisfred@gmail.com
License: GNU GPL v2
Platform: UNKNOWN
Requires: scipy
Requires: ctypes
Provides: mirage
Provides: autoqueue
